yamldown/__init__.py
yamldown/yamldown.py
yamldown_unicode-0.0.1.dist-info/LICENSE
yamldown_unicode-0.0.1.dist-info/METADATA
yamldown_unicode-0.0.1.dist-info/WHEEL
yamldown_unicode-0.0.1.dist-info/top_level.txt
yamldown_unicode-0.0.1.dist-info/RECORD
